odoo/addons/stock_account_anglo_saxon_cogs_kit/README.rst
odoo/addons/stock_account_anglo_saxon_cogs_kit/__init__.py
odoo/addons/stock_account_anglo_saxon_cogs_kit/__manifest__.py
odoo/addons/stock_account_anglo_saxon_cogs_kit/i18n/it.po
odoo/addons/stock_account_anglo_saxon_cogs_kit/i18n/stock_account_anglo_saxon_cogs_kit.pot
odoo/addons/stock_account_anglo_saxon_cogs_kit/models/__init__.py
odoo/addons/stock_account_anglo_saxon_cogs_kit/models/account_move_line.py
odoo/addons/stock_account_anglo_saxon_cogs_kit/readme/CONTRIBUTORS.rst
odoo/addons/stock_account_anglo_saxon_cogs_kit/readme/DESCRIPTION.rst
odoo/addons/stock_account_anglo_saxon_cogs_kit/static/description/icon.png
odoo/addons/stock_account_anglo_saxon_cogs_kit/static/description/index.html
odoo/addons/stock_account_anglo_saxon_cogs_kit/tests/__init__.py
odoo/addons/stock_account_anglo_saxon_cogs_kit/tests/test_stock_account_anglo_saxon_cogs_kit.py
odoo_addon_stock_account_anglo_saxon_cogs_kit-16.0.2.0.0.2.dist-info/METADATA
odoo_addon_stock_account_anglo_saxon_cogs_kit-16.0.2.0.0.2.dist-info/WHEEL
odoo_addon_stock_account_anglo_saxon_cogs_kit-16.0.2.0.0.2.dist-info/top_level.txt
odoo_addon_stock_account_anglo_saxon_cogs_kit-16.0.2.0.0.2.dist-info/RECORD
